Logisim_Verilog/binary_arcade.v
module counter(input[0:3] user_input,input[0:3] random_number,input clk,input reset,output[0:3] x);
    
    //since counter is being employed, output must require memory of previous input, so reg is required
    reg[0:3] x; 
    
    //triggered if clock is at positive edge (0->1)
    always @(posedge clk) 
    begin
        //reset the counter
        if (reset==1) begin
            x=4'b0000; //make counter 0
        end
        //if user_input==random number, counter is incremented by 1
        else if( user_input==random_number )begin
            x=x+4'b0001; //counter+=1
            if (x==4'b1010) $finish; //if counter reaches 10 once incremented, the execution ends
        end
    end

    //triggered if clock is at negative edge (1->0)
    always @(negedge clk) 
    begin
        //reset the counter
        if (reset==1) begin
            x=4'b0000; //make counter 0
        end
        //if user_input==random number, counter is incremented by 1
        else if( user_input==random_number )begin
            x=x+4'b0001; //counter+=1
            if (x==4'b1010) $finish; //if counter reaches 10 once incremented, the execution ends
        end
    end 
endmodule

Logisim_Verilog/binary_arcade_tb.v
`include "binary_arcade.v" //including the module file

module binary_arcade_tb;

//all variables used in this code

reg[0:3] user_input; //this is the user input (binary representation of randomly generated number)

reg[0:3] random_number; //this is the random number generated in decimal form

reg clk; //this is the clock

reg reset; //reset button, 1 if we need to reset counter, 0 if counter is operating as usual

wire[0:3] x; //counter, only incremented if user_input=correct binary representation of random_number

//instantiation

counter uut( 
    .user_input(user_input),
    .random_number(random_number),
    .clk(clk),
    .reset(reset),
    .x(x) 
);

//starting the code

initial begin

    //making the vcd(gtkwave) file
    $dumpfile("binary_arcade.vcd");
    $dumpvars(0,binary_arcade_tb);
    
    //global reset
    
    clk=0; //initializing clock

    reset=1; //to reset counter to 0
    
    user_input=$random; //user_input for the sake of this code is a randomly generated number
    
    #100; //waiting 100ns for global reset

    //displaying clock,user_input,random_number and counter
    $display("\n");
    $display("Clock | Random_Number |   User_Input  | Counter\n");
    $monitor("  %d   |     %4d      |      %4b     | %4d",clk,random_number,user_input,x); 
    
    //start counter
    reset=0;
    
end
always #5 clk=~clk; //clock is being triggered every 5 ns
always #5 random_number=$random; //b is being randomly generated every time clock triggers
endmodule

Verilog/binary_arcade.vcd
$date
	Fri Oct 13 22:55:59 2023
$end
$version
	Icarus Verilog
$end
$timescale
	1s
$end
$scope module binary_arcade_tb $end
$var wire 4 ! x [0:3] $end
$var reg 1 " clk $end
$var reg 4 # random_number [0:3] $end
$var reg 1 $ reset $end
$var reg 4 % user_input [0:3] $end
$scope module uut $end
$var wire 1 " clk $end
$var wire 4 & random_number [0:3] $end
$var wire 1 $ reset $end
$var wire 4 ' user_input [0:3] $end
$var reg 4 ( x [0:3] $end
$upscope $end
$upscope $end
$enddefinitions $end
$comment Show the parameter values. $end
$dumpall
$end
#0
$dumpvars
b0 (
b100 '
bx &
b100 %
1$
bx #
0"
b0 !
$end
#5
b1 #
b1 &
1"
#10
b1001 #
b1001 &
0"
#15
b11 #
b11 &
1"
#20
b1101 #
b1101 &
0"
#25
1"
#30
b101 #
b101 &
0"
#35
b10 #
b10 &
1"
#40
b1 #
b1 &
0"
#45
b1101 #
b1101 &
1"
#50
b110 #
b110 &
0"
#55
b1101 #
b1101 &
1"
#60
0"
#65
b1100 #
b1100 &
1"
#70
b1001 #
b1001 &
0"
#75
b110 #
b110 &
1"
#80
b101 #
b101 &
0"
#85
b1010 #
b1010 &
1"
#90
b101 #
b101 &
0"
#95
b111 #
b111 &
1"
#100
b10 #
b10 &
0"
0$
#105
b1111 #
b1111 &
1"
#110
b10 #
b10 &
0"
#115
b1110 #
b1110 &
1"
#120
b1000 #
b1000 &
0"
#125
b101 #
b101 &
1"
#130
b1100 #
b1100 &
0"
#135
b1101 #
b1101 &
1"
#140
0"
#145
b101 #
b101 &
1"
#150
b11 #
b11 &
0"
#155
b1010 #
b1010 &
1"
#160
b0 #
b0 &
0"
#165
1"
#170
b1010 #
b1010 &
0"
#175
b1101 #
b1101 &
1"
#180
b110 #
b110 &
0"
#185
b11 #
b11 &
1"
#190
b1101 #
b1101 &
0"
#195
b11 #
b11 &
1"
#200
b1011 #
b1011 &
0"
#205
b101 #
b101 &
1"
#210
b10 #
b10 &
0"
#215
b1110 #
b1110 &
1"
#220
b1101 #
b1101 &
0"
#225
b1111 #
b1111 &
1"
#230
b11 #
b11 &
0"
#235
b1010 #
b1010 &
1"
#240
0"
#245
b1100 #
b1100 &
1"
#250
b10 #
b10 &
0"
#255
b1010 #
b1010 &
1"
#260
b1 #
b1 &
0"
#265
b1000 #
b1000 &
1"
#270
0"
#275
b1001 #
b1001 &
1"
#280
b1011 #
b1011 &
0"
#285
b110 #
b110 &
1"
#290
0"
#295
b1110 #
b1110 &
1"
#300
b1100 #
b1100 &
0"
#305
b1010 #
b1010 &
1"
#310
b1011 #
b1011 &
0"
#315
b1 #
b1 &
1"
#320
b101 #
b101 &
0"
#325
b1111 #
b1111 &
1"
#330
b1011 #
b1011 &
0"
#335
b1010 #
b1010 &
1"
#340
b1110 #
b1110 &
0"
#345
b101 #
b101 &
1"
#350
b1 #
b1 &
0"
#355
b1001 #
b1001 &
1"
#360
b10 #
b10 &
0"
#365
b1100 #
b1100 &
1"
#370
b1111 #
b1111 &
0"
#375
1"
#380
b1000 #
b1000 &
0"
#385
b111 #
b111 &
1"
#390
b1111 #
b1111 &
0"
#395
b1100 #
b1100 &
1"
#400
b1011 #
b1011 &
0"
#405
b1001 #
b1001 &
1"
#410
0"
#415
b0 #
b0 &
1"
#420
b111 #
b111 &
0"
#425
b1 #
b1 &
1"
#430
b110 #
b110 &
0"
#435
b1100 #
b1100 &
1"
#440
b10 #
b10 &
0"
#445
b1000 #
b1000 &
1"
#450
b111 #
b111 &
0"
#455
b1101 #
b1101 &
1"
#460
b10 #
b10 &
0"
#465
b1110 #
b1110 &
1"
#470
b1101 #
b1101 &
0"
#475
b1001 #
b1001 &
1"
#480
b1111 #
b1111 &
0"
#485
b11 #
b11 &
1"
#490
b101 #
b101 &
0"
#495
b1000 #
b1000 &
1"
#500
b1011 #
b1011 &
0"
#505
b1001 #
b1001 &
1"
#510
b1111 #
b1111 &
0"
#515
b1010 #
b1010 &
1"
#520
b1000 #
b1000 &
0"
#525
b110 #
b110 &
1"
#530
b1110 #
b1110 &
0"
#535
b1100 #
b1100 &
1"
#540
b1010 #
b1010 &
0"
#545
b110 #
b110 &
1"
#550
b11 #
b11 &
0"
#555
1"
#560
b1111 #
b1111 &
0"
#565
b11 #
b11 &
1"
#570
b1111 #
b1111 &
0"
#575
b1 !
b1 (
b100 #
b100 &
1"
#580
b111 #
b111 &
0"
#585
b1011 #
b1011 &
1"
#590
b110 #
b110 &
0"
#595
b1010 #
b1010 &
1"
#600
b1001 #
b1001 &
0"
#605
b1101 #
b1101 &
1"
#610
b1010 #
b1010 &
0"
#615
b101 #
b101 &
1"
#620
0"
#625
b1111 #
b1111 &
1"
#630
b1001 #
b1001 &
0"
#635
b10 !
b10 (
b100 #
b100 &
1"
#640
b0 #
b0 &
0"
#645
b1010 #
b1010 &
1"
#650
b1011 #
b1011 &
0"
#655
b1110 #
b1110 &
1"
#660
b1100 #
b1100 &
0"
#665
b1010 #
b1010 &
1"
#670
b1101 #
b1101 &
0"
#675
b11 #
b11 &
1"
#680
b110 #
b110 &
0"
#685
b1110 #
b1110 &
1"
#690
b111 #
b111 &
0"
#695
b1010 #
b1010 &
1"
#700
b110 #
b110 &
0"
#705
b1000 #
b1000 &
1"
#710
b1001 #
b1001 &
0"
#715
b1000 #
b1000 &
1"
#720
b11 !
b11 (
b100 #
b100 &
0"
#725
b11 #
b11 &
1"
#730
b100 !
b100 (
b100 #
b100 &
0"
#735
b1001 #
b1001 &
1"
#740
b1011 #
b1011 &
0"
#745
b1101 #
b1101 &
1"
#750
b1001 #
b1001 &
0"
#755
b1101 #
b1101 &
1"
#760
b110 #
b110 &
0"
#765
b1010 #
b1010 &
1"
#770
b110 #
b110 &
0"
#775
b101 #
b101 &
1"
#780
b110 #
b110 &
0"
#785
b101 !
b101 (
b100 #
b100 &
1"
#790
b111 #
b111 &
0"
#795
b1001 #
b1001 &
1"
#800
b110 !
b110 (
b100 #
b100 &
0"
#805
b1000 #
b1000 &
1"
#810
0"
#815
b1101 #
b1101 &
1"
#820
b111 #
b111 &
0"
#825
b1110 #
b1110 &
1"
#830
b1000 #
b1000 &
0"
#835
b1100 #
b1100 &
1"
#840
b1101 #
b1101 &
0"
#845
b1001 #
b1001 &
1"
#850
b1100 #
b1100 &
0"
#855
b110 #
b110 &
1"
#860
b1010 #
b1010 &
0"
#865
b1101 #
b1101 &
1"
#870
b110 #
b110 &
0"
#875
b0 #
b0 &
1"
#880
b11 #
b11 &
0"
#885
b1010 #
b1010 &
1"
#890
b1110 #
b1110 &
0"
#895
b1010 #
b1010 &
1"
#900
b101 #
b101 &
0"
#905
b1010 #
b1010 &
1"
#910
b1001 #
b1001 &
0"
#915
b111 #
b111 &
1"
#920
b110 #
b110 &
0"
#925
b0 #
b0 &
1"
#930
b110 #
b110 &
0"
#935
1"
#940
b1101 #
b1101 &
0"
#945
b1100 #
b1100 &
1"
#950
b110 #
b110 &
0"
#955
b1000 #
b1000 &
1"
#960
b1110 #
b1110 &
0"
#965
b1011 #
b1011 &
1"
#970
b1111 #
b1111 &
0"
#975
b1001 #
b1001 &
1"
#980
b1010 #
b1010 &
0"
#985
b1 #
b1 &
1"
#990
b111 #
b111 &
0"
#995
b1 #
b1 &
1"
#1000
b110 #
b110 &
0"
#1005
b0 #
b0 &
1"
#1010
b101 #
b101 &
0"
#1015
1"
#1020
b1001 #
b1001 &
0"
#1025
b1 #
b1 &
1"
#1030
b101 #
b101 &
0"
#1035
b1000 #
b1000 &
1"
#1040
b1011 #
b1011 &
0"
#1045
b11 #
b11 &
1"
#1050
b1100 #
b1100 &
0"
#1055
b1010 #
b1010 &
1"
#1060
b1110 #
b1110 &
0"
#1065
b1000 #
b1000 &
1"
#1070
b1001 #
b1001 &
0"
#1075
b1 #
b1 &
1"
#1080
b1110 #
b1110 &
0"
#1085
b110 #
b110 &
1"
#1090
b1111 #
b1111 &
0"
#1095
b1010 #
b1010 &
1"
#1100
0"
#1105
b1101 #
b1101 &
1"
#1110
b1110 #
b1110 &
0"
#1115
b1000 #
b1000 &
1"
#1120
b1001 #
b1001 &
0"
#1125
b1000 #
b1000 &
1"
#1130
b1010 #
b1010 &
0"
#1135
b11 #
b11 &
1"
#1140
b1011 #
b1011 &
0"
#1145
b111 #
b111 &
1"
#1150
b110 #
b110 &
0"
#1155
b1010 #
b1010 &
1"
#1160
b111 !
b111 (
b100 #
b100 &
0"
#1165
b1001 #
b1001 &
1"
#1170
b10 #
b10 &
0"
#1175
b1000 !
b1000 (
b100 #
b100 &
1"
#1180
b1111 #
b1111 &
0"
#1185
b110 #
b110 &
1"
#1190
b1010 #
b1010 &
0"
#1195
b10 #
b10 &
1"
#1200
0"
#1205
b1101 #
b1101 &
1"
#1210
b1001 !
b1001 (
b100 #
b100 &
0"
#1215
b1010 !
b1010 (
1"
